TineFlutterAppium/__init__.py
TineFlutterAppium/keywords/__init__.py
TineFlutterAppium/keywords/_support.py
TineFlutterAppium/keywords/_supportelement.py
TineFlutterAppium/keywords/keywordgroup.py
TineFlutterAppium-1.3.0.dist-info/METADATA
TineFlutterAppium-1.3.0.dist-info/WHEEL
TineFlutterAppium-1.3.0.dist-info/top_level.txt
TineFlutterAppium-1.3.0.dist-info/RECORD
