Metadata-Version: 2.1
Name: TineFlutterAppium
Version: 1.3.0
Summary: This Library is support to appiumlibrary and appiumflutterlibrary
Home-page: https://github.com/pornpawit08/TineFlutterAppium.git
Author: Pornpawit Suttha
Author-email: pornpawit14suttha@gmail.com
License: UNKNOWN
Platform: UNKNOWN
Classifier: Programming Language :: Python :: 3
Classifier: License :: OSI Approved :: MIT License
Classifier: Operating System :: OS Independent
Requires-Python: >=3.6
Requires-Dist: robotframework >=3.0
